setup.cfg
setup.py
MacSGP/__init__.py
MacSGP/model.py
MacSGP/networks.py
MacSGP/utils.py
MacSGP/vis.py
MacSGP.egg-info/PKG-INFO
MacSGP.egg-info/SOURCES.txt
MacSGP.egg-info/dependency_links.txt
MacSGP.egg-info/not-zip-safe
MacSGP.egg-info/requires.txt
MacSGP.egg-info/top_level.txt