Metadata-Version: 2.2
Name: MacSGP
Version: 0.1
Summary: MacSGP is a scalable statistical and computational approach for MApping Cell-type-specific Spatial Gene Programs (SGPs) in spatial transcriptomic (ST) data.
Home-page: https://github.com/YangLabHKUST/MacSGP
Author: Yeqin Zeng
Author-email: yzengbj@connect.ust.hk
License: MIT
Requires-Dist: anndata==0.11.3
Requires-Dist: matplotlib==3.10.1
Requires-Dist: numpy==1.26.4
Requires-Dist: pandas==2.2.3
Requires-Dist: scanpy==1.11.0
Requires-Dist: scipy==1.15.2
Requires-Dist: torch==2.5.1
Requires-Dist: torch-geometric==2.6.1
Requires-Dist: tqdm==4.67.1
Dynamic: author
Dynamic: author-email
Dynamic: home-page
Dynamic: license
Dynamic: requires-dist
Dynamic: summary
